pytest_import_check/__init__.py
pytest_import_check/importer.py
pytest_import_check/plugin.py
pytest_import_check-0.0.4.dist-info/entry_points.txt
pytest_import_check-0.0.4.dist-info/COPYING
pytest_import_check-0.0.4.dist-info/WHEEL
pytest_import_check-0.0.4.dist-info/METADATA
pytest_import_check-0.0.4.dist-info/RECORD
