Metadata-Version: 2.1
Name: pytest-import-check
Version: 0.0.4
Summary: pytest plugin to check whether Python modules can be imported
Author-email: Michał Górny <mgorny@gentoo.org>
Requires-Python: >=3.9
Classifier: Development Status :: 3 - Alpha
Classifier: Framework :: Pytest
Classifier: Intended Audience :: Developers
Classifier: License :: OSI Approved :: GNU General Public License v2 or later (GPLv2+)
Classifier: Programming Language :: Python :: 3 :: Only
Classifier: Topic :: Software Development :: Testing
Requires-Dist: pytest >= 8.1
Requires-Dist: meson ; extra == "test"
Requires-Dist: ninja ; extra == "test"
Requires-Dist: setuptools ; extra == "test"
Project-URL: Homepage, https://github.com/projg2/pytest-import-check/
Provides-Extra: test
